week3/reference/advanced_mac/mac_v2.v
// Reference: production-leaning MAC unit (강화판)
//
// 기본 mac.v 대비 8가지 개선:
//   1. Parameterized DATA_WIDTH / ACC_WIDTH  — INT4/INT8/INT16 재사용 가능
//   2. Active-low reset (rst_n)              — 산업 표준
//   3. Enable 신호 (en)                       — stall / power saving
//   4. Clear accumulator (clear_acc)          — 새 dot product 시퀀스 시작
//   5. Valid 신호 pipeline (in_valid → acc_valid)  — 외부 모듈과 handshake
//   6. 2-stage pipeline (곱 → 누적)           — 고주파 (>300 MHz) 동작 가능
//   7. Saturation + overflow flag             — silent wrap 방지
//   8. `initial` 블록 없음                    — 합성 가능, testbench 가 dump 담당

module mac_v2 #(
    parameter DATA_WIDTH = 8,
    parameter ACC_WIDTH  = 32
) (
    input  wire                          clk,
    input  wire                          rst_n,      // active-low reset
    input  wire                          en,         // global enable
    input  wire                          clear_acc,  // 이번 입력부터 acc 새로 시작
    input  wire signed [DATA_WIDTH-1:0]  in_data,
    input  wire signed [DATA_WIDTH-1:0]  weight,
    input  wire                          in_valid,   // 입력이 유효함
    output reg  signed [ACC_WIDTH-1:0]   acc,
    output reg                           overflow,   // saturation 발생 표시
    output reg                           acc_valid   // acc 가 유효한 결과임
);

    localparam PROD_WIDTH = 2 * DATA_WIDTH;
    localparam signed [ACC_WIDTH-1:0] ACC_MAX = {1'b0, {(ACC_WIDTH-1){1'b1}}};  // 2^(ACC_WIDTH-1) - 1
    localparam signed [ACC_WIDTH-1:0] ACC_MIN = {1'b1, {(ACC_WIDTH-1){1'b0}}};  // -2^(ACC_WIDTH-1)

    // ===========================================================
    // Stage 1: 곱 (1 cycle latency)
    // ===========================================================
    reg signed [PROD_WIDTH-1:0] prod_reg;
    reg                          prod_valid;
    reg                          prod_clear;

    always @(posedge clk or negedge rst_n) begin
        if (!rst_n) begin
            prod_reg   <= {PROD_WIDTH{1'b0}};
            prod_valid <= 1'b0;
            prod_clear <= 1'b0;
        end else if (en) begin
            prod_reg   <= in_data * weight;
            prod_valid <= in_valid;
            prod_clear <= clear_acc & in_valid;
        end
    end

    // 곱 결과를 ACC_WIDTH+1 비트로 sign-extend (overflow 감지용 1비트 여유)
    wire signed [ACC_WIDTH:0] prod_ext =
        {{(ACC_WIDTH-PROD_WIDTH+1){prod_reg[PROD_WIDTH-1]}}, prod_reg};

    // ===========================================================
    // Stage 2: 누적 + saturation (1 cycle latency)
    // ===========================================================
    wire signed [ACC_WIDTH:0] acc_ext = {acc[ACC_WIDTH-1], acc};                  // sign-extend acc to 33-bit
    wire signed [ACC_WIDTH:0] acc_base = prod_clear ? {(ACC_WIDTH+1){1'b0}} : acc_ext;
    wire signed [ACC_WIDTH:0] acc_next_raw = acc_base + prod_ext;

    // Overflow 감지: 33-bit 결과의 sign bit (bit 32) 와 32-bit truncation 시 sign bit (bit 31) 가 다르면 overflow
    wire overflow_detected = (acc_next_raw[ACC_WIDTH] != acc_next_raw[ACC_WIDTH-1]);

    always @(posedge clk or negedge rst_n) begin
        if (!rst_n) begin
            acc       <= {ACC_WIDTH{1'b0}};
            overflow  <= 1'b0;
            acc_valid <= 1'b0;
        end else if (en) begin
            if (prod_valid) begin
                if (overflow_detected) begin
                    acc      <= acc_next_raw[ACC_WIDTH] ? ACC_MIN : ACC_MAX;
                    overflow <= 1'b1;
                end else begin
                    acc      <= acc_next_raw[ACC_WIDTH-1:0];
                    // overflow 는 sticky — 한 번 1 이면 reset 까지 유지
                end
            end
            acc_valid <= prod_valid;
        end
    end

`ifndef SYNTHESIS
    initial begin
        $dumpfile("dump.vcd");
        $dumpvars(0, mac_v2);
    end
`endif

endmodule

week3/reference/advanced_mac/dump.vcd
$date
	Fri May 22 13:01:06 2026
$end
$version
	Icarus Verilog
$end
$timescale
	1ps
$end
$scope module mac_v2 $end
$var wire 1 ! clear_acc $end
$var wire 1 " clk $end
$var wire 1 # en $end
$var wire 8 $ in_data [7:0] $end
$var wire 1 % in_valid $end
$var wire 1 & overflow_detected $end
$var wire 1 ' rst_n $end
$var wire 8 ( weight [7:0] $end
$var wire 33 ) prod_ext [32:0] $end
$var wire 33 * acc_next_raw [32:0] $end
$var wire 33 + acc_ext [32:0] $end
$var wire 33 , acc_base [32:0] $end
$var parameter 32 - ACC_MAX $end
$var parameter 32 . ACC_MIN $end
$var parameter 32 / ACC_WIDTH $end
$var parameter 32 0 DATA_WIDTH $end
$var parameter 64 1 PROD_WIDTH $end
$var reg 32 2 acc [31:0] $end
$var reg 1 3 acc_valid $end
$var reg 1 4 overflow $end
$var reg 1 5 prod_clear $end
$var reg 16 6 prod_reg [15:0] $end
$var reg 1 7 prod_valid $end
$upscope $end
$enddefinitions $end
$comment Show the parameter values. $end
$dumpall
b10000 1
b1000 0
b100000 /
b10000000000000000000000000000000 .
b1111111111111111111111111111111 -
$end
#0
$dumpvars
07
b0 6
05
04
03
b0 2
b0 ,
b0 +
b0 *
b0 )
b0 (
0'
0&
0%
b0 $
1#
1"
0!
$end
#5000
0"
#10000
1'
1"
#15000
0"
#20000
1%
b101 (
b11 $
1"
#25000
0"
#30000
b100 (
b10 $
b1111 *
b1111 )
17
b1111 6
1"
#35000
0"
#40000
b110 (
b1 $
b1111 ,
b10111 *
b1000 )
b1111 +
b1000 6
13
b1111 2
1"
#45000
0"
#50000
0%
b0 (
b0 $
b10111 ,
b10111 +
b11101 *
b110 )
b10111 2
b110 6
1"
#55000
0"
#60000
b11101 ,
b11101 *
b0 )
b11101 +
07
b0 6
b11101 2
1"
#65000
0"
#70000
03
1"
#75000
0"
#80000
1"
#80001
b0 *
b0 ,
b0 +
b0 2
0'
#85001
0"
#90001
1"
#95001
0"
#100001
1'
1"
#105001
0"
#110001
1%
b11 (
b101 $
1"
#115001
0"
#120001
0%
b0 (
b0 $
b1111 *
b1111 )
17
b1111 6
1"
#125001
0"
#130001
b1111 ,
b1111 *
b0 )
b1111 +
07
b0 6
13
b1111 2
1"
#135001
0"
#140001
03
1"
#145001
0"
#150001
1%
b10100 (
b1010 $
0#
1"
#155001
0"
#160001
1"
#165001
0"
#170001
1"
#175001
0"
#180001
1"
#185001
0"
#190001
1"
#195001
0"
#200001
1"
#200002
b0 *
b0 ,
b0 +
b0 2
0%
b0 (
b0 $
1#
0'
#205002
0"
#210002
1"
#215002
0"
#220002
1'
1"
#225002
0"
#230002
1%
b11 (
b101 $
1"
#235002
0"
#240002
b10 (
b100 $
b1111 *
b1111 )
17
b1111 6
1"
#245002
0"
#250002
0%
b0 (
b0 $
b1111 ,
b1111 +
b10111 *
b1000 )
13
b1111 2
b1000 6
1"
#255002
0"
#260002
b10111 ,
b10111 *
b0 )
b10111 +
07
b0 6
b10111 2
1"
#265002
0"
#270002
03
1"
#275002
0"
#280002
1!
1%
b1000 (
b111 $
1"
#285002
0"
#290002
0!
0%
b0 (
b0 $
b0 ,
b111000 *
b111000 )
15
17
b111000 6
1"
#295002
0"
#300002
b111000 ,
b111000 *
b0 )
b111000 +
05
07
b0 6
13
b111000 2
1"
#305002
0"
#310002
03
1"
#315002
0"
#320002
1"
#320003
b0 *
b0 ,
b0 +
b0 2
0'
#325003
0"
#330003
1"
#335003
0"
#340003
1'
1"
#345003
0"
#350003
1%
b1111111 (
b1111111 $
1"
#355003
0"
#360003
b11111100000001 *
b11111100000001 )
17
b11111100000001 6
1"
#365003
0"
#370003
b111111000000010 *
b11111100000001 ,
b11111100000001 +
13
b11111100000001 2
1"
#375003
0"
#380003
b1011110100000011 *
b111111000000010 ,
b111111000000010 +
b111111000000010 2
1"
#385003
0"
#390003
b1111110000000100 *
b1011110100000011 ,
b1011110100000011 +
b1011110100000011 2
1"
#395003
0"
#400003
b10011101100000101 *
b1111110000000100 ,
b1111110000000100 +
b1111110000000100 2
1"
#405003
0"
#410003
b10111101000000110 *
b10011101100000101 ,
b10011101100000101 +
b10011101100000101 2
1"
#415003
0"
#420003
b11011100100000111 *
b10111101000000110 ,
b10111101000000110 +
b10111101000000110 2
1"
#425003
0"
#430003
b11111100000001000 *
b11011100100000111 ,
b11011100100000111 +
b11011100100000111 2
1"
#435003
0"
#440003
b100011011100001001 *
b11111100000001000 ,
b11111100000001000 +
b11111100000001000 2
1"
#445003
0"
#450003
b100111011000001010 *
b100011011100001001 ,
b100011011100001001 +
b100011011100001001 2
1"
#455003
0"
#460003
b101011010100001011 *
b100111011000001010 ,
b100111011000001010 +
b100111011000001010 2
1"
#465003
0"
#470003
b101111010000001100 *
b101011010100001011 ,
b101011010100001011 +
b101011010100001011 2
1"
#475003
0"
#480003
b110011001100001101 *
b101111010000001100 ,
b101111010000001100 +
b101111010000001100 2
1"
#485003
0"
#490003
b110111001000001110 *
b110011001100001101 ,
b110011001100001101 +
b110011001100001101 2
1"
#495003
0"
#500003
b111011000100001111 *
b110111001000001110 ,
b110111001000001110 +
b110111001000001110 2
1"
#505003
0"
#510003
b111111000000010000 *
b111011000100001111 ,
b111011000100001111 +
b111011000100001111 2
1"
#515003
0"
#520003
b1000010111100010001 *
b111111000000010000 ,
b111111000000010000 +
b111111000000010000 2
1"
#525003
0"
#530003
b1000110111000010010 *
b1000010111100010001 ,
b1000010111100010001 +
b1000010111100010001 2
1"
#535003
0"
#540003
b1001010110100010011 *
b1000110111000010010 ,
b1000110111000010010 +
b1000110111000010010 2
1"
#545003
0"
#550003
b1001110110000010100 *
b1001010110100010011 ,
b1001010110100010011 +
b1001010110100010011 2
1"
#555003
0"
#560003
b1010010101100010101 *
b1001110110000010100 ,
b1001110110000010100 +
b1001110110000010100 2
1"
#565003
0"
#570003
b1010110101000010110 *
b1010010101100010101 ,
b1010010101100010101 +
b1010010101100010101 2
1"
#575003
0"
#580003
b1011010100100010111 *
b1010110101000010110 ,
b1010110101000010110 +
b1010110101000010110 2
1"
#585003
0"
#590003
b1011110100000011000 *
b1011010100100010111 ,
b1011010100100010111 +
b1011010100100010111 2
1"
#595003
0"
#600003
b1100010011100011001 *
b1011110100000011000 ,
b1011110100000011000 +
b1011110100000011000 2
1"
#605003
0"
#610003
b1100110011000011010 *
b1100010011100011001 ,
b1100010011100011001 +
b1100010011100011001 2
1"
#615003
0"
#620003
b1101010010100011011 *
b1100110011000011010 ,
b1100110011000011010 +
b1100110011000011010 2
1"
#625003
0"
#630003
b1101110010000011100 *
b1101010010100011011 ,
b1101010010100011011 +
b1101010010100011011 2
1"
#635003
0"
#640003
b1110010001100011101 *
b1101110010000011100 ,
b1101110010000011100 +
b1101110010000011100 2
1"
#645003
0"
#650003
b1110110001000011110 *
b1110010001100011101 ,
b1110010001100011101 +
b1110010001100011101 2
1"
#655003
0"
#660003
b1111010000100011111 *
b1110110001000011110 ,
b1110110001000011110 +
b1110110001000011110 2
1"
#665003
0"
#670003
b1111110000000100000 *
b1111010000100011111 ,
b1111010000100011111 +
b1111010000100011111 2
1"
#675003
0"
#680003
b10000001111100100001 *
b1111110000000100000 ,
b1111110000000100000 +
b1111110000000100000 2
1"
#685003
0"
#690003
b10000101111000100010 *
b10000001111100100001 ,
b10000001111100100001 +
b10000001111100100001 2
1"
#695003
0"
#700003
b10001001110100100011 *
b10000101111000100010 ,
b10000101111000100010 +
b10000101111000100010 2
1"
#705003
0"
#710003
b10001101110000100100 *
b10001001110100100011 ,
b10001001110100100011 +
b10001001110100100011 2
1"
#715003
0"
#720003
b10010001101100100101 *
b10001101110000100100 ,
b10001101110000100100 +
b10001101110000100100 2
1"
#725003
0"
#730003
b10010101101000100110 *
b10010001101100100101 ,
b10010001101100100101 +
b10010001101100100101 2
1"
#735003
0"
#740003
b10011001100100100111 *
b10010101101000100110 ,
b10010101101000100110 +
b10010101101000100110 2
1"
#745003
0"
#750003
b10011101100000101000 *
b10011001100100100111 ,
b10011001100100100111 +
b10011001100100100111 2
1"
#755003
0"
#760003
b10100001011100101001 *
b10011101100000101000 ,
b10011101100000101000 +
b10011101100000101000 2
1"
#765003
0"
#770003
b10100101011000101010 *
b10100001011100101001 ,
b10100001011100101001 +
b10100001011100101001 2
1"
#775003
0"
#780003
b10101001010100101011 *
b10100101011000101010 ,
b10100101011000101010 +
b10100101011000101010 2
1"
#785003
0"
#790003
b10101101010000101100 *
b10101001010100101011 ,
b10101001010100101011 +
b10101001010100101011 2
1"
#795003
0"
#800003
b10110001001100101101 *
b10101101010000101100 ,
b10101101010000101100 +
b10101101010000101100 2
1"
#805003
0"
#810003
b10110101001000101110 *
b10110001001100101101 ,
b10110001001100101101 +
b10110001001100101101 2
1"
#815003
0"
#820003
b10111001000100101111 *
b10110101001000101110 ,
b10110101001000101110 +
b10110101001000101110 2
1"
#825003
0"
#830003
b10111101000000110000 *
b10111001000100101111 ,
b10111001000100101111 +
b10111001000100101111 2
1"
#835003
0"
#840003
b11000000111100110001 *
b10111101000000110000 ,
b10111101000000110000 +
b10111101000000110000 2
1"
#845003
0"
#850003
b11000100111000110010 *
b11000000111100110001 ,
b11000000111100110001 +
b11000000111100110001 2
1"
#855003
0"
#860003
b11001000110100110011 *
b11000100111000110010 ,
b11000100111000110010 +
b11000100111000110010 2
1"
#865003
0"
#870003
b11001100110000110100 *
b11001000110100110011 ,
b11001000110100110011 +
b11001000110100110011 2
1"
#875003
0"
#880003
b11010000101100110101 *
b11001100110000110100 ,
b11001100110000110100 +
b11001100110000110100 2
1"
#885003
0"
#890003
b11010100101000110110 *
b11010000101100110101 ,
b11010000101100110101 +
b11010000101100110101 2
1"
#895003
0"
#900003
b11011000100100110111 *
b11010100101000110110 ,
b11010100101000110110 +
b11010100101000110110 2
1"
#905003
0"
#910003
b11011100100000111000 *
b11011000100100110111 ,
b11011000100100110111 +
b11011000100100110111 2
1"
#915003
0"
#920003
b11100000011100111001 *
b11011100100000111000 ,
b11011100100000111000 +
b11011100100000111000 2
1"
#925003
0"
#930003
b11100100011000111010 *
b11100000011100111001 ,
b11100000011100111001 +
b11100000011100111001 2
1"
#935003
0"
#940003
b11101000010100111011 *
b11100100011000111010 ,
b11100100011000111010 +
b11100100011000111010 2
1"
#945003
0"
#950003
b11101100010000111100 *
b11101000010100111011 ,
b11101000010100111011 +
b11101000010100111011 2
1"
#955003
0"
#960003
b11110000001100111101 *
b11101100010000111100 ,
b11101100010000111100 +
b11101100010000111100 2
1"
#965003
0"
#970003
b11110100001000111110 *
b11110000001100111101 ,
b11110000001100111101 +
b11110000001100111101 2
1"
#975003
0"
#980003
b11111000000100111111 *
b11110100001000111110 ,
b11110100001000111110 +
b11110100001000111110 2
1"
#985003
0"
#990003
b11111100000001000000 *
b11111000000100111111 ,
b11111000000100111111 +
b11111000000100111111 2
1"
#995003
0"
#1000003
b11111111111101000001 *
b11111100000001000000 ,
b11111100000001000000 +
b11111100000001000000 2
1"
#1005003
0"
#1010003
b100000011111001000010 *
b11111111111101000001 ,
b11111111111101000001 +
b11111111111101000001 2
1"
#1015003
0"
#1020003
b100000111110101000011 *
b100000011111001000010 ,
b100000011111001000010 +
b100000011111001000010 2
1"
#1025003
0"
#1030003
b100001011110001000100 *
b100000111110101000011 ,
b100000111110101000011 +
b100000111110101000011 2
1"
#1035003
0"
#1040003
b100001111101101000101 *
b100001011110001000100 ,
b100001011110001000100 +
b100001011110001000100 2
1"
#1045003
0"
#1050003
b100010011101001000110 *
b100001111101101000101 ,
b100001111101101000101 +
b100001111101101000101 2
1"
#1055003
0"
#1060003
b100010111100101000111 *
b100010011101001000110 ,
b100010011101001000110 +
b100010011101001000110 2
1"
#1065003
0"
#1070003
b100011011100001001000 *
b100010111100101000111 ,
b100010111100101000111 +
b100010111100101000111 2
1"
#1075003
0"
#1080003
b100011111011101001001 *
b100011011100001001000 ,
b100011011100001001000 +
b100011011100001001000 2
1"
#1085003
0"
#1090003
b100100011011001001010 *
b100011111011101001001 ,
b100011111011101001001 +
b100011111011101001001 2
1"
#1095003
0"
#1100003
b100100111010101001011 *
b100100011011001001010 ,
b100100011011001001010 +
b100100011011001001010 2
1"
#1105003
0"
#1110003
b100101011010001001100 *
b100100111010101001011 ,
b100100111010101001011 +
b100100111010101001011 2
1"
#1115003
0"
#1120003
b100101111001101001101 *
b100101011010001001100 ,
b100101011010001001100 +
b100101011010001001100 2
1"
#1125003
0"
#1130003
b100110011001001001110 *
b100101111001101001101 ,
b100101111001101001101 +
b100101111001101001101 2
1"
#1135003
0"
#1140003
b100110111000101001111 *
b100110011001001001110 ,
b100110011001001001110 +
b100110011001001001110 2
1"
#1145003
0"
#1150003
b100111011000001010000 *
b100110111000101001111 ,
b100110111000101001111 +
b100110111000101001111 2
1"
#1155003
0"
#1160003
b100111110111101010001 *
b100111011000001010000 ,
b100111011000001010000 +
b100111011000001010000 2
1"
#1165003
0"
#1170003
b101000010111001010010 *
b100111110111101010001 ,
b100111110111101010001 +
b100111110111101010001 2
1"
#1175003
0"
#1180003
b101000110110101010011 *
b101000010111001010010 ,
b101000010111001010010 +
b101000010111001010010 2
1"
#1185003
0"
#1190003
b101001010110001010100 *
b101000110110101010011 ,
b101000110110101010011 +
b101000110110101010011 2
1"
#1195003
0"
#1200003
b101001110101101010101 *
b101001010110001010100 ,
b101001010110001010100 +
b101001010110001010100 2
1"
#1205003
0"
#1210003
b101010010101001010110 *
b101001110101101010101 ,
b101001110101101010101 +
b101001110101101010101 2
1"
#1215003
0"
#1220003
b101010110100101010111 *
b101010010101001010110 ,
b101010010101001010110 +
b101010010101001010110 2
1"
#1225003
0"
#1230003
b101011010100001011000 *
b101010110100101010111 ,
b101010110100101010111 +
b101010110100101010111 2
1"
#1235003
0"
#1240003
b101011110011101011001 *
b101011010100001011000 ,
b101011010100001011000 +
b101011010100001011000 2
1"
#1245003
0"
#1250003
b101100010011001011010 *
b101011110011101011001 ,
b101011110011101011001 +
b101011110011101011001 2
1"
#1255003
0"
#1260003
b101100110010101011011 *
b101100010011001011010 ,
b101100010011001011010 +
b101100010011001011010 2
1"
#1265003
0"
#1270003
b101101010010001011100 *
b101100110010101011011 ,
b101100110010101011011 +
b101100110010101011011 2
1"
#1275003
0"
#1280003
b101101110001101011101 *
b101101010010001011100 ,
b101101010010001011100 +
b101101010010001011100 2
1"
#1285003
0"
#1290003
b101110010001001011110 *
b101101110001101011101 ,
b101101110001101011101 +
b101101110001101011101 2
1"
#1295003
0"
#1300003
b101110110000101011111 *
b101110010001001011110 ,
b101110010001001011110 +
b101110010001001011110 2
1"
#1305003
0"
#1310003
b101111010000001100000 *
b101110110000101011111 ,
b101110110000101011111 +
b101110110000101011111 2
1"
#1315003
0"
#1320003
b101111101111101100001 *
b101111010000001100000 ,
b101111010000001100000 +
b101111010000001100000 2
1"
#1325003
0"
#1330003
b110000001111001100010 *
b101111101111101100001 ,
b101111101111101100001 +
b101111101111101100001 2
1"
#1335003
0"
#1340003
b110000101110101100011 *
b110000001111001100010 ,
b110000001111001100010 +
b110000001111001100010 2
1"
#1345003
0"
#1350003
0%
b0 (
b0 $
b110001001110001100100 *
b110000101110101100011 ,
b110000101110101100011 +
b110000101110101100011 2
1"
#1355003
0"
#1360003
b110001001110001100100 ,
b110001001110001100100 +
b110001001110001100100 *
b0 )
b110001001110001100100 2
07
b0 6
1"
#1365003
0"
#1370003
03
1"
#1375003
0"
#1380003
1"
#1380004
b0 *
b0 ,
b0 +
b0 2
0'
#1385004
0"
#1390004
1"
#1395004
0"
#1400004
1'
1"
#1405004
0"
#1410004
1%
b101 (
b11 $
1"
#1415004
0"
#1420004
0%
b0 (
b0 $
b1111 *
b1111 )
17
b1111 6
1"
#1425004
0"
#1430004
b1111 ,
b1111 +
b1111 *
b0 )
13
b1111 2
07
b0 6
1"
#1435004
0"
#1440004
03
1"
#1445004
0"
#1450004
1"
#1455004
0"
#1460004
1"
#1465004
0"
#1470004
1"
#1470005
b0 *
b0 ,
b0 +
b0 2
0'
#1475005
0"
#1480005
1"
#1485005
0"
#1490005
1'
1"
#1495005
0"
#1500005
1%
b100110 (
b11011100 $
1"
#1505005
0"
#1510005
b11101110 (
b100010 $
b111111111111111111111101010101000 *
b111111111111111111111101010101000 )
17
b1111101010101000 6
1"
#1515005
0"
#1520005
b11101111 (
b11010110 $
0&
b111111111111111111111101010101000 ,
b111111111111111111111101010101000 +
b111111111111111111111100001000100 *
b111111111111111111111110110011100 )
13
b11111111111111111111101010101000 2
b1111110110011100 6
1"
#1525005
0"
#1530005
b11010100 (
b11011010 $
b111111111111111111111100001000100 ,
b111111111111111111111101100001110 *
b1011001010 )
b111111111111111111111100001000100 +
b1011001010 6
b11111111111111111111100001000100 2
1"
#1535005
0"
#1540005
b11111000 (
b11011 $
b111111111111111111111101100001110 ,
b111111111111111111111101100001110 +
b110010110 *
b11010001000 )
b11111111111111111111101100001110 2
b11010001000 6
1"
#1545005
0"
#1550005
b101111 (
b11001 $
0&
b110010110 ,
b10111110 *
b111111111111111111111111100101000 )
b110010110 +
b1111111100101000 6
b110010110 2
1"
#1555005
0"
#1560005
b10101 (
b110001 $
b10111110 ,
b10111110 +
b10101010101 *
b10010010111 )
b10111110 2
b10010010111 6
1"
#1565005
0"
#1570005
b100011 (
b110 $
b10101010101 ,
b100101011010 *
b10000000101 )
b10101010101 +
b10000000101 6
b10101010101 2
1"
#1575005
0"
#1580005
b101011 (
b1111 $
b100101011010 ,
b100101011010 +
b101000101100 *
b11010010 )
b100101011010 2
b11010010 6
1"
#1585005
0"
#1590005
b1101 (
b11110011 $
b101000101100 ,
b110010110001 *
b1010000101 )
b101000101100 +
b1010000101 6
b101000101100 2
1"
#1595005
0"
#1600005
b100000 (
b11101111 $
b110010110001 ,
b110010110001 +
b110000001000 *
b111111111111111111111111101010111 )
b110010110001 2
b1111111101010111 6
1"
#1605005
0"
#1610005
b10110 (
b11111001 $
b110000001000 ,
b100111101000 *
b111111111111111111111110111100000 )
b110000001000 +
b1111110111100000 6
b110000001000 2
1"
#1615005
0"
#1620005
b100010 (
b11010110 $
b100111101000 ,
b100111101000 +
b100101001110 *
b111111111111111111111111101100110 )
b100111101000 2
b1111111101100110 6
1"
#1625005
0"
#1630005
b11101001 (
b11111000 $
b100101001110 ,
b1110111010 *
b111111111111111111111101001101100 )
b100101001110 +
b1111101001101100 6
b100101001110 2
1"
#1635005
0"
#1640005
b11010100 (
b11001 $
b1110111010 ,
b1110111010 +
b10001110010 *
b10111000 )
b1110111010 2
b10111000 6
1"
#1645005
0"
#1650005
b11001 (
b100011 $
b10001110010 ,
b100110 *
b111111111111111111111101110110100 )
b10001110010 +
b1111101110110100 6
b10001110010 2
1"
#1655005
0"
#1660005
b10100 (
b11010110 $
b100110 ,
b100110 +
b1110010001 *
b1101101011 )
b100110 2
b1101101011 6
1"
#1665005
0"
#1670005
b1100 (
b11010011 $
b1110010001 ,
b1001001 *
b111111111111111111111110010111000 )
b1110010001 +
b1111110010111000 6
b1110010001 2
1"
#1675005
0"
#1680005
b101101 (
b10 $
b1001001 ,
b1001001 +
b111111111111111111111111000101101 *
b111111111111111111111110111100100 )
b1001001 2
b1111110111100100 6
1"
#1685005
0"
#1690005
b11111010 (
b10011 $
0&
b111111111111111111111111000101101 ,
b111111111111111111111111010000111 *
b1011010 )
b111111111111111111111111000101101 +
b1011010 6
b11111111111111111111111000101101 2
1"
#1695005
0"
#1700005
b11101011 (
b101001 $
b111111111111111111111111010000111 ,
b111111111111111111111111010000111 +
b111111111111111111111111000010101 *
b111111111111111111111111110001110 )
b11111111111111111111111010000111 2
b1111111110001110 6
1"
#1705005
0"
#1710005
b11011110 (
b0 $
b111111111111111111111111000010101 ,
b111111111111111111111101010111000 *
b111111111111111111111110010100011 )
b111111111111111111111111000010101 +
b1111110010100011 6
b11111111111111111111111000010101 2
1"
#1715005
0"
#1720005
b11010001 (
b111 $
b111111111111111111111101010111000 ,
b111111111111111111111101010111000 +
b111111111111111111111101010111000 *
b0 )
b11111111111111111111101010111000 2
b0 6
1"
#1725005
0"
#1730005
b11001 (
b11100001 $
b111111111111111111111100101101111 *
b111111111111111111111111010110111 )
b1111111010110111 6
1"
#1735005
0"
#1740005
b11111101 (
b10100 $
b111111111111111111111100101101111 ,
b111111111111111111111100101101111 +
b111111111111111111111011001101000 *
b111111111111111111111110011111001 )
b11111111111111111111100101101111 2
b1111110011111001 6
1"
#1745005
0"
#1750005
b10011 (
b11001110 $
b111111111111111111111011001101000 ,
b111111111111111111111011000101100 *
b111111111111111111111111111000100 )
b111111111111111111111011001101000 +
b1111111111000100 6
b11111111111111111111011001101000 2
1"
#1755005
0"
#1760005
b11000 (
b11011000 $
b111111111111111111111011000101100 ,
b111111111111111111111011000101100 +
b111111111111111111111001001110110 *
b111111111111111111111110001001010 )
b11111111111111111111011000101100 2
b1111110001001010 6
1"
#1765005
0"
#1770005
b11001 (
b11010111 $
b111111111111111111111001001110110 ,
b111111111111111111110111010110110 *
b111111111111111111111110001000000 )
b111111111111111111111001001110110 +
b1111110001000000 6
b11111111111111111111001001110110 2
1"
#1775005
0"
#1780005
b11 (
b100 $
b111111111111111111110111010110110 ,
b111111111111111111110111010110110 +
b111111111111111111110101010110101 *
b111111111111111111111101111111111 )
b11111111111111111110111010110110 2
b1111101111111111 6
1"
#1785005
0"
#1790005
b11100010 (
b11101110 $
b111111111111111111110101010110101 ,
b111111111111111111110101011000001 *
b1100 )
b111111111111111111110101010110101 +
b1100 6
b11111111111111111110101010110101 2
1"
#1795005
0"
#1800005
b11110100 (
b11011 $
b111111111111111111110101011000001 ,
b111111111111111111110101011000001 +
b111111111111111111110110011011101 *
b1000011100 )
b11111111111111111110101011000001 2
b1000011100 6
1"
#1805005
0"
#1810005
b11010100 (
b10 $
b111111111111111111110110011011101 ,
b111111111111111111110101110011001 *
b111111111111111111111111010111100 )
b111111111111111111110110011011101 +
b1111111010111100 6
b11111111111111111110110011011101 2
1"
#1815005
0"
#1820005
b11111000 (
b101010 $
b111111111111111111110101110011001 ,
b111111111111111111110101110011001 +
b111111111111111111110101101000001 *
b111111111111111111111111110101000 )
b11111111111111111110101110011001 2
b1111111110101000 6
1"
#1825005
0"
#1830005
b10000 (
b11110100 $
b111111111111111111110101101000001 ,
b111111111111111111110100111110001 *
b111111111111111111111111010110000 )
b111111111111111111110101101000001 +
b1111111010110000 6
b11111111111111111110101101000001 2
1"
#1835005
0"
#1840005
b11111111 (
b11001 $
b111111111111111111110100111110001 ,
b111111111111111111110100111110001 +
b111111111111111111110100100110001 *
b111111111111111111111111101000000 )
b11111111111111111110100111110001 2
b1111111101000000 6
1"
#1845005
0"
#1850005
b101110 (
b101111 $
b111111111111111111110100100110001 ,
b111111111111111111110100100011000 *
b111111111111111111111111111100111 )
b111111111111111111110100100110001 +
b1111111111100111 6
b11111111111111111110100100110001 2
1"
#1855005
0"
#1860005
b11100101 (
b11101000 $
b111111111111111111110100100011000 ,
b111111111111111111110100100011000 +
b111111111111111111111000110001010 *
b100001110010 )
b11111111111111111110100100011000 2
b100001110010 6
1"
#1865005
0"
#1870005
b111 (
b10111 $
b111111111111111111111000110001010 ,
b111111111111111111111010000010010 *
b1010001000 )
b111111111111111111111000110001010 +
b1010001000 6
b11111111111111111111000110001010 2
1"
#1875005
0"
#1880005
b11010111 (
b11100000 $
b111111111111111111111010000010010 ,
b111111111111111111111010000010010 +
b111111111111111111111010010110011 *
b10100001 )
b11111111111111111111010000010010 2
b10100001 6
1"
#1885005
0"
#1890005
b11111010 (
b11001 $
b111111111111111111111010010110011 ,
b111111111111111111111100111010011 *
b10100100000 )
b111111111111111111111010010110011 +
b10100100000 6
b11111111111111111111010010110011 2
1"
#1895005
0"
#1900005
b101110 (
b1000 $
b111111111111111111111100111010011 ,
b111111111111111111111100111010011 +
b111111111111111111111100100111101 *
b111111111111111111111111101101010 )
b11111111111111111111100111010011 2
b1111111101101010 6
1"
#1905005
0"
#1910005
b1101 (
b10101 $
b111111111111111111111100100111101 ,
b111111111111111111111101010101101 *
b101110000 )
b111111111111111111111100100111101 +
b101110000 6
b11111111111111111111100100111101 2
1"
#1915005
0"
#1920005
b10010 (
b1101 $
b111111111111111111111101010101101 ,
b111111111111111111111101010101101 +
b111111111111111111111101110111110 *
b100010001 )
b11111111111111111111101010101101 2
b100010001 6
1"
#1925005
0"
#1930005
b11010111 (
b0 $
b111111111111111111111101110111110 ,
b111111111111111111111110010101000 *
b11101010 )
b111111111111111111111101110111110 +
b11101010 6
b11111111111111111111101110111110 2
1"
#1935005
0"
#1940005
b100 (
b11100 $
b111111111111111111111110010101000 ,
b111111111111111111111110010101000 +
b111111111111111111111110010101000 *
b0 )
b11111111111111111111110010101000 2
b0 6
1"
#1945005
0"
#1950005
b10001 (
b11010101 $
b111111111111111111111110100011000 *
b1110000 )
b1110000 6
1"
#1955005
0"
#1960005
b11010011 (
b11111 $
b111111111111111111111110100011000 ,
b111111111111111111111110100011000 +
b111111111111111111111101000111101 *
b111111111111111111111110100100101 )
b11111111111111111111110100011000 2
b1111110100100101 6
1"
#1965005
0"
#1970005
b11101000 (
b11110100 $
b111111111111111111111101000111101 ,
b111111111111111111111010011001010 *
b111111111111111111111101010001101 )
b111111111111111111111101000111101 +
b1111101010001101 6
b11111111111111111111101000111101 2
1"
#1975005
0"
#1980005
b11011 (
b11010110 $
b111111111111111111111010011001010 ,
b111111111111111111111010011001010 +
b111111111111111111111010111101010 *
b100100000 )
b11111111111111111111010011001010 2
b100100000 6
1"
#1985005
0"
#1990005
b11010100 (
b11010011 $
b111111111111111111111010111101010 ,
b111111111111111111111000101111100 *
b111111111111111111111101110010010 )
b111111111111111111111010111101010 +
b1111101110010010 6
b11111111111111111111010111101010 2
1"
#1995005
0"
#2000005
b11010 (
b11101 $
b111111111111111111111000101111100 ,
b111111111111111111111000101111100 +
b111111111111111111111100100111000 *
b11110111100 )
b11111111111111111111000101111100 2
b11110111100 6
1"
#2005005
0"
