week3/reference/02_mac_verilog/mac.v
// Reference: signed INT8 × INT8 MAC with INT32 accumulator
//
// Single multiply-accumulate unit:
//   acc <- acc + (in_data * weight)   on every rising clock edge
//
// Width discipline:
//   - inputs are signed 8-bit  (-128..127)
//   - product is naturally signed 16-bit
//   - accumulator is signed 32-bit (auto sign-extension when added)

module mac (
    input  wire                clk,
    input  wire                rst,
    input  wire signed  [7:0]  in_data,
    input  wire signed  [7:0]  weight,
    output reg  signed  [31:0] acc
);
    always @(posedge clk) begin
        if (rst)
            acc <= 32'sd0;
        else
            acc <= acc + (in_data * weight);
    end

    // Waveform dump for GTKWave (`make WAVES=1` 또는 cocotb 환경변수)
    initial begin
        $dumpfile("dump.vcd");
        $dumpvars(0, mac);
    end
endmodule

week3/reference/02_mac_verilog/dump.vcd
$date
	Sun May  3 22:43:23 2026
$end
$version
	Icarus Verilog
$end
$timescale
	1ps
$end
$scope module mac $end
$var wire 1 ! clk $end
$var wire 8 " in_data [7:0] $end
$var wire 1 # rst $end
$var wire 8 $ weight [7:0] $end
$var reg 32 % acc [31:0] $end
$upscope $end
$enddefinitions $end
$comment Show the parameter values. $end
$dumpall
$end
#0
$dumpvars
b0 %
b0 $
1#
b0 "
1!
$end
#5000
0!
#10000
0#
1!
#15000
0!
#20000
b101 $
b11 "
1!
#25000
0!
#30000
b100 $
b10 "
b1111 %
1!
#35000
0!
#40000
b110 $
b1 "
b10111 %
1!
#45000
0!
#50000
b0 $
b0 "
b11101 %
1!
#55000
0!
#60000
1!
#60001
1#
#65001
0!
#70001
b0 %
1!
#75001
0!
#80001
0#
1!
#85001
0!
#90001
b101 $
b11111101 "
1!
#95001
0!
#100001
b11111001 $
b100 "
b11111111111111111111111111110001 %
1!
#105001
0!
#110001
b11111000 $
b11111110 "
b11111111111111111111111111010101 %
1!
#115001
0!
#120001
b1100 $
b1010 "
b11111111111111111111111111100101 %
1!
#125001
0!
#130001
b0 $
b0 "
b1011101 %
1!
#135001
0!
#140001
1!
#140002
1#
#145002
0!
#150002
b0 %
1!
#155002
0!
#160002
0#
1!
#165002
0!
#170002
b1 $
b1 "
1!
#175002
0!
#180002
b1 %
1!
#185002
0!
#190002
b10 %
1!
#195002
0!
#200002
b11 %
1!
#205002
0!
#210002
b100 %
1!
#215002
0!
#220002
b101 %
1!
#225002
0!
#230002
b110 %
1!
#235002
0!
#240002
b111 %
1!
#245002
0!
#250002
b1000 %
1!
#255002
0!
#260002
b1001 %
1!
#265002
0!
#270002
b1010 %
1!
#275002
0!
#280002
b1011 %
1!
#285002
0!
#290002
b1100 %
1!
#295002
0!
#300002
b1101 %
1!
#305002
0!
#310002
b1110 %
1!
#315002
0!
#320002
b1111 %
1!
#325002
0!
#330002
b10000 %
1!
#335002
0!
#340002
b10001 %
1!
#345002
0!
#350002
b10010 %
1!
#355002
0!
#360002
b10011 %
1!
#365002
0!
#370002
b10100 %
1!
#375002
0!
#380002
b10101 %
1!
#385002
0!
#390002
b10110 %
1!
#395002
0!
#400002
b10111 %
1!
#405002
0!
#410002
b11000 %
1!
#415002
0!
#420002
b11001 %
1!
#425002
0!
#430002
b11010 %
1!
#435002
0!
#440002
b11011 %
1!
#445002
0!
#450002
b11100 %
1!
#455002
0!
#460002
b11101 %
1!
#465002
0!
#470002
b11110 %
1!
#475002
0!
#480002
b11111 %
1!
#485002
0!
#490002
b100000 %
1!
#495002
0!
#500002
b100001 %
1!
#505002
0!
#510002
b100010 %
1!
#515002
0!
#520002
b100011 %
1!
#525002
0!
#530002
b100100 %
1!
#535002
0!
#540002
b100101 %
1!
#545002
0!
#550002
b100110 %
1!
#555002
0!
#560002
b100111 %
1!
#565002
0!
#570002
b101000 %
1!
#575002
0!
#580002
b101001 %
1!
#585002
0!
#590002
b101010 %
1!
#595002
0!
#600002
b101011 %
1!
#605002
0!
#610002
b101100 %
1!
#615002
0!
#620002
b101101 %
1!
#625002
0!
#630002
b101110 %
1!
#635002
0!
#640002
b101111 %
1!
#645002
0!
#650002
b110000 %
1!
#655002
0!
#660002
b110001 %
1!
#665002
0!
#670002
b110010 %
1!
#675002
0!
#680002
b110011 %
1!
#685002
0!
#690002
b110100 %
1!
#695002
0!
#700002
b110101 %
1!
#705002
0!
#710002
b110110 %
1!
#715002
0!
#720002
b110111 %
1!
#725002
0!
#730002
b111000 %
1!
#735002
0!
#740002
b111001 %
1!
#745002
0!
#750002
b111010 %
1!
#755002
0!
#760002
b111011 %
1!
#765002
0!
#770002
b111100 %
1!
#775002
0!
#780002
b111101 %
1!
#785002
0!
#790002
b111110 %
1!
#795002
0!
#800002
b111111 %
1!
#805002
0!
#810002
b1000000 %
1!
#815002
0!
#820002
b1000001 %
1!
#825002
0!
#830002
b1000010 %
1!
#835002
0!
#840002
b1000011 %
1!
#845002
0!
#850002
b1000100 %
1!
#855002
0!
#860002
b1000101 %
1!
#865002
0!
#870002
b1000110 %
1!
#875002
0!
#880002
b1000111 %
1!
#885002
0!
#890002
b1001000 %
1!
#895002
0!
#900002
b1001001 %
1!
#905002
0!
#910002
b1001010 %
1!
#915002
0!
#920002
b1001011 %
1!
#925002
0!
#930002
b1001100 %
1!
#935002
0!
#940002
b1001101 %
1!
#945002
0!
#950002
b1001110 %
1!
#955002
0!
#960002
b1001111 %
1!
#965002
0!
#970002
b1010000 %
1!
#975002
0!
#980002
b1010001 %
1!
#985002
0!
#990002
b1010010 %
1!
#995002
0!
#1000002
b1010011 %
1!
#1005002
0!
#1010002
b1010100 %
1!
#1015002
0!
#1020002
b1010101 %
1!
#1025002
0!
#1030002
b1010110 %
1!
#1035002
0!
#1040002
b1010111 %
1!
#1045002
0!
#1050002
b1011000 %
1!
#1055002
0!
#1060002
b1011001 %
1!
#1065002
0!
#1070002
b1011010 %
1!
#1075002
0!
#1080002
b1011011 %
1!
#1085002
0!
#1090002
b1011100 %
1!
#1095002
0!
#1100002
b1011101 %
1!
#1105002
0!
#1110002
b1011110 %
1!
#1115002
0!
#1120002
b1011111 %
1!
#1125002
0!
#1130002
b1100000 %
1!
#1135002
0!
#1140002
b1100001 %
1!
#1145002
0!
#1150002
b1100010 %
1!
#1155002
0!
#1160002
b1100011 %
1!
#1165002
0!
#1170002
b1100100 %
1!
#1175002
0!
#1180002
b1100101 %
1!
#1185002
0!
#1190002
b1100110 %
1!
#1195002
0!
#1200002
b1100111 %
1!
#1205002
0!
#1210002
b1101000 %
1!
#1215002
0!
#1220002
b1101001 %
1!
#1225002
0!
#1230002
b1101010 %
1!
#1235002
0!
#1240002
b1101011 %
1!
#1245002
0!
#1250002
b1101100 %
1!
#1255002
0!
#1260002
b1101101 %
1!
#1265002
0!
#1270002
b1101110 %
1!
#1275002
0!
#1280002
b1101111 %
1!
#1285002
0!
#1290002
b1110000 %
1!
#1295002
0!
#1300002
b1110001 %
1!
#1305002
0!
#1310002
b1110010 %
1!
#1315002
0!
#1320002
b1110011 %
1!
#1325002
0!
#1330002
b1110100 %
1!
#1335002
0!
#1340002
b1110101 %
1!
#1345002
0!
#1350002
b1110110 %
1!
#1355002
0!
#1360002
b1110111 %
1!
#1365002
0!
#1370002
b1111000 %
1!
#1375002
0!
#1380002
b1111001 %
1!
#1385002
0!
#1390002
b1111010 %
1!
#1395002
0!
#1400002
b1111011 %
1!
#1405002
0!
#1410002
b1111100 %
1!
#1415002
0!
#1420002
b1111101 %
1!
#1425002
0!
#1430002
b1111110 %
1!
#1435002
0!
#1440002
b1111111 %
1!
#1445002
0!
#1450002
b10000000 %
1!
#1455002
0!
#1460002
b10000001 %
1!
#1465002
0!
#1470002
b10000010 %
1!
#1475002
0!
#1480002
b10000011 %
1!
#1485002
0!
#1490002
b10000100 %
1!
#1495002
0!
#1500002
b10000101 %
1!
#1505002
0!
#1510002
b10000110 %
1!
#1515002
0!
#1520002
b10000111 %
1!
#1525002
0!
#1530002
b10001000 %
1!
#1535002
0!
#1540002
b10001001 %
1!
#1545002
0!
#1550002
b10001010 %
1!
#1555002
0!
#1560002
b10001011 %
1!
#1565002
0!
#1570002
b10001100 %
1!
#1575002
0!
#1580002
b10001101 %
1!
#1585002
0!
#1590002
b10001110 %
1!
#1595002
0!
#1600002
b10001111 %
1!
#1605002
0!
#1610002
b10010000 %
1!
#1615002
0!
#1620002
b10010001 %
1!
#1625002
0!
#1630002
b10010010 %
1!
#1635002
0!
#1640002
b10010011 %
1!
#1645002
0!
#1650002
b10010100 %
1!
#1655002
0!
#1660002
b10010101 %
1!
#1665002
0!
#1670002
b10010110 %
1!
#1675002
0!
#1680002
b10010111 %
1!
#1685002
0!
#1690002
b10011000 %
1!
#1695002
0!
#1700002
b10011001 %
1!
#1705002
0!
#1710002
b10011010 %
1!
#1715002
0!
#1720002
b10011011 %
1!
#1725002
0!
#1730002
b10011100 %
1!
#1735002
0!
#1740002
b10011101 %
1!
#1745002
0!
#1750002
b10011110 %
1!
#1755002
0!
#1760002
b10011111 %
1!
#1765002
0!
#1770002
b10100000 %
1!
#1775002
0!
#1780002
b10100001 %
1!
#1785002
0!
#1790002
b10100010 %
1!
#1795002
0!
#1800002
b10100011 %
1!
#1805002
0!
#1810002
b10100100 %
1!
#1815002
0!
#1820002
b10100101 %
1!
#1825002
0!
#1830002
b10100110 %
1!
#1835002
0!
#1840002
b10100111 %
1!
#1845002
0!
#1850002
b10101000 %
1!
#1855002
0!
#1860002
b10101001 %
1!
#1865002
0!
#1870002
b10101010 %
1!
#1875002
0!
#1880002
b10101011 %
1!
#1885002
0!
#1890002
b10101100 %
1!
#1895002
0!
#1900002
b10101101 %
1!
#1905002
0!
#1910002
b10101110 %
1!
#1915002
0!
#1920002
b10101111 %
1!
#1925002
0!
#1930002
b10110000 %
1!
#1935002
0!
#1940002
b10110001 %
1!
#1945002
0!
#1950002
b10110010 %
1!
#1955002
0!
#1960002
b10110011 %
1!
#1965002
0!
#1970002
b10110100 %
1!
#1975002
0!
#1980002
b10110101 %
1!
#1985002
0!
#1990002
b10110110 %
1!
#1995002
0!
#2000002
b10110111 %
1!
#2005002
0!
#2010002
b10111000 %
1!
#2015002
0!
#2020002
b10111001 %
1!
#2025002
0!
#2030002
b10111010 %
1!
#2035002
0!
#2040002
b10111011 %
1!
#2045002
0!
#2050002
b10111100 %
1!
#2055002
0!
#2060002
b10111101 %
1!
#2065002
0!
#2070002
b10111110 %
1!
#2075002
0!
#2080002
b10111111 %
1!
#2085002
0!
#2090002
b11000000 %
1!
#2095002
0!
#2100002
b11000001 %
1!
#2105002
0!
#2110002
b11000010 %
1!
#2115002
0!
#2120002
b11000011 %
1!
#2125002
0!
#2130002
b11000100 %
1!
#2135002
0!
#2140002
b11000101 %
1!
#2145002
0!
#2150002
b11000110 %
1!
#2155002
0!
#2160002
b11000111 %
1!
#2165002
0!
#2170002
b11001000 %
1!
#2175002
0!
#2180002
b11001001 %
1!
#2185002
0!
#2190002
b11001010 %
1!
#2195002
0!
#2200002
b11001011 %
1!
#2205002
0!
#2210002
b11001100 %
1!
#2215002
0!
#2220002
b11001101 %
1!
#2225002
0!
#2230002
b11001110 %
1!
#2235002
0!
#2240002
b11001111 %
1!
#2245002
0!
#2250002
b11010000 %
1!
#2255002
0!
#2260002
b11010001 %
1!
#2265002
0!
#2270002
b11010010 %
1!
#2275002
0!
#2280002
b11010011 %
1!
#2285002
0!
#2290002
b11010100 %
1!
#2295002
0!
#2300002
b11010101 %
1!
#2305002
0!
#2310002
b11010110 %
1!
#2315002
0!
#2320002
b11010111 %
1!
#2325002
0!
#2330002
b11011000 %
1!
#2335002
0!
#2340002
b11011001 %
1!
#2345002
0!
#2350002
b11011010 %
1!
#2355002
0!
#2360002
b11011011 %
1!
#2365002
0!
#2370002
b11011100 %
1!
#2375002
0!
#2380002
b11011101 %
1!
#2385002
0!
#2390002
b11011110 %
1!
#2395002
0!
#2400002
b11011111 %
1!
#2405002
0!
#2410002
b11100000 %
1!
#2415002
0!
#2420002
b11100001 %
1!
#2425002
0!
#2430002
b11100010 %
1!
#2435002
0!
#2440002
b11100011 %
1!
#2445002
0!
#2450002
b11100100 %
1!
#2455002
0!
#2460002
b11100101 %
1!
#2465002
0!
#2470002
b11100110 %
1!
#2475002
0!
#2480002
b11100111 %
1!
#2485002
0!
#2490002
b11101000 %
1!
#2495002
0!
#2500002
b11101001 %
1!
#2505002
0!
#2510002
b11101010 %
1!
#2515002
0!
#2520002
b11101011 %
1!
#2525002
0!
#2530002
b11101100 %
1!
#2535002
0!
#2540002
b11101101 %
1!
#2545002
0!
#2550002
b11101110 %
1!
#2555002
0!
#2560002
b11101111 %
1!
#2565002
0!
#2570002
b11110000 %
1!
#2575002
0!
#2580002
b11110001 %
1!
#2585002
0!
#2590002
b11110010 %
1!
#2595002
0!
#2600002
b11110011 %
1!
#2605002
0!
#2610002
b11110100 %
1!
#2615002
0!
#2620002
b11110101 %
1!
#2625002
0!
#2630002
b11110110 %
1!
#2635002
0!
#2640002
b11110111 %
1!
#2645002
0!
#2650002
b11111000 %
1!
#2655002
0!
#2660002
b11111001 %
1!
#2665002
0!
#2670002
b11111010 %
1!
#2675002
0!
#2680002
b11111011 %
1!
#2685002
0!
#2690002
b11111100 %
1!
#2695002
0!
#2700002
b11111101 %
1!
#2705002
0!
#2710002
b11111110 %
1!
#2715002
0!
#2720002
b11111111 %
1!
#2725002
0!
#2730002
b100000000 %
1!
#2735002
0!
#2740002
b100000001 %
1!
#2745002
0!
#2750002
b100000010 %
1!
#2755002
0!
#2760002
b100000011 %
1!
#2765002
0!
#2770002
b100000100 %
1!
#2775002
0!
#2780002
b100000101 %
1!
#2785002
0!
#2790002
b100000110 %
1!
#2795002
0!
#2800002
b100000111 %
1!
#2805002
0!
#2810002
b100001000 %
1!
#2815002
0!
#2820002
b100001001 %
1!
#2825002
0!
#2830002
b100001010 %
1!
#2835002
0!
#2840002
b100001011 %
1!
#2845002
0!
#2850002
b100001100 %
1!
#2855002
0!
#2860002
b100001101 %
1!
#2865002
0!
#2870002
b100001110 %
1!
#2875002
0!
#2880002
b100001111 %
1!
#2885002
0!
#2890002
b100010000 %
1!
#2895002
0!
#2900002
b100010001 %
1!
#2905002
0!
#2910002
b100010010 %
1!
#2915002
0!
#2920002
b100010011 %
1!
#2925002
0!
#2930002
b100010100 %
1!
#2935002
0!
#2940002
b100010101 %
1!
#2945002
0!
#2950002
b100010110 %
1!
#2955002
0!
#2960002
b100010111 %
1!
#2965002
0!
#2970002
b100011000 %
1!
#2975002
0!
#2980002
b100011001 %
1!
#2985002
0!
#2990002
b100011010 %
1!
#2995002
0!
#3000002
b100011011 %
1!
#3005002
0!
#3010002
b100011100 %
1!
#3015002
0!
#3020002
b100011101 %
1!
#3025002
0!
#3030002
b100011110 %
1!
#3035002
0!
#3040002
b100011111 %
1!
#3045002
0!
#3050002
b100100000 %
1!
#3055002
0!
#3060002
b100100001 %
1!
#3065002
0!
#3070002
b100100010 %
1!
#3075002
0!
#3080002
b100100011 %
1!
#3085002
0!
#3090002
b100100100 %
1!
#3095002
0!
#3100002
b100100101 %
1!
#3105002
0!
#3110002
b100100110 %
1!
#3115002
0!
#3120002
b100100111 %
1!
#3125002
0!
#3130002
b100101000 %
1!
#3135002
0!
#3140002
b100101001 %
1!
#3145002
0!
#3150002
b100101010 %
1!
#3155002
0!
#3160002
b100101011 %
1!
#3165002
0!
#3170002
b100101100 %
1!
#3175002
0!
#3180002
b100101101 %
1!
#3185002
0!
#3190002
b100101110 %
1!
#3195002
0!
#3200002
b100101111 %
1!
#3205002
0!
#3210002
b100110000 %
1!
#3215002
0!
#3220002
b100110001 %
1!
#3225002
0!
#3230002
b100110010 %
1!
#3235002
0!
#3240002
b100110011 %
1!
#3245002
0!
#3250002
b100110100 %
1!
#3255002
0!
#3260002
b100110101 %
1!
#3265002
0!
#3270002
b100110110 %
1!
#3275002
0!
#3280002
b100110111 %
1!
#3285002
0!
#3290002
b100111000 %
1!
#3295002
0!
#3300002
b100111001 %
1!
#3305002
0!
#3310002
b100111010 %
1!
#3315002
0!
#3320002
b100111011 %
1!
#3325002
0!
#3330002
b100111100 %
1!
#3335002
0!
#3340002
b100111101 %
1!
#3345002
0!
#3350002
b100111110 %
1!
#3355002
0!
#3360002
b100111111 %
1!
#3365002
0!
#3370002
b101000000 %
1!
#3375002
0!
#3380002
b101000001 %
1!
#3385002
0!
#3390002
b101000010 %
1!
#3395002
0!
#3400002
b101000011 %
1!
#3405002
0!
#3410002
b101000100 %
1!
#3415002
0!
#3420002
b101000101 %
1!
#3425002
0!
#3430002
b101000110 %
1!
#3435002
0!
#3440002
b101000111 %
1!
#3445002
0!
#3450002
b101001000 %
1!
#3455002
0!
#3460002
b101001001 %
1!
#3465002
0!
#3470002
b101001010 %
1!
#3475002
0!
#3480002
b101001011 %
1!
#3485002
0!
#3490002
b101001100 %
1!
#3495002
0!
#3500002
b101001101 %
1!
#3505002
0!
#3510002
b101001110 %
1!
#3515002
0!
#3520002
b101001111 %
1!
#3525002
0!
#3530002
b101010000 %
1!
#3535002
0!
#3540002
b101010001 %
1!
#3545002
0!
#3550002
b101010010 %
1!
#3555002
0!
#3560002
b101010011 %
1!
#3565002
0!
#3570002
b101010100 %
1!
#3575002
0!
#3580002
b101010101 %
1!
#3585002
0!
#3590002
b101010110 %
1!
#3595002
0!
#3600002
b101010111 %
1!
#3605002
0!
#3610002
b101011000 %
1!
#3615002
0!
#3620002
b101011001 %
1!
#3625002
0!
#3630002
b101011010 %
1!
#3635002
0!
#3640002
b101011011 %
1!
#3645002
0!
#3650002
b101011100 %
1!
#3655002
0!
#3660002
b101011101 %
1!
#3665002
0!
#3670002
b101011110 %
1!
#3675002
0!
#3680002
b101011111 %
1!
#3685002
0!
#3690002
b101100000 %
1!
#3695002
0!
#3700002
b101100001 %
1!
#3705002
0!
#3710002
b101100010 %
1!
#3715002
0!
#3720002
b101100011 %
1!
#3725002
0!
#3730002
b101100100 %
1!
#3735002
0!
#3740002
b101100101 %
1!
#3745002
0!
#3750002
b101100110 %
1!
#3755002
0!
#3760002
b101100111 %
1!
#3765002
0!
#3770002
b101101000 %
1!
#3775002
0!
#3780002
b101101001 %
1!
#3785002
0!
#3790002
b101101010 %
1!
#3795002
0!
#3800002
b101101011 %
1!
#3805002
0!
#3810002
b101101100 %
1!
#3815002
0!
#3820002
b101101101 %
1!
#3825002
0!
#3830002
b101101110 %
1!
#3835002
0!
#3840002
b101101111 %
1!
#3845002
0!
#3850002
b101110000 %
1!
#3855002
0!
#3860002
b101110001 %
1!
#3865002
0!
#3870002
b101110010 %
1!
#3875002
0!
#3880002
b101110011 %
1!
#3885002
0!
#3890002
b101110100 %
1!
#3895002
0!
#3900002
b101110101 %
1!
#3905002
0!
#3910002
b101110110 %
1!
#3915002
0!
#3920002
b101110111 %
1!
#3925002
0!
#3930002
b101111000 %
1!
#3935002
0!
#3940002
b101111001 %
1!
#3945002
0!
#3950002
b101111010 %
1!
#3955002
0!
#3960002
b101111011 %
1!
#3965002
0!
#3970002
b101111100 %
1!
#3975002
0!
#3980002
b101111101 %
1!
#3985002
0!
#3990002
b101111110 %
1!
#3995002
0!
#4000002
b101111111 %
1!
#4005002
0!
#4010002
b110000000 %
1!
#4015002
0!
#4020002
b110000001 %
1!
#4025002
0!
#4030002
b110000010 %
1!
#4035002
0!
#4040002
b110000011 %
1!
#4045002
0!
#4050002
b110000100 %
1!
#4055002
0!
#4060002
b110000101 %
1!
#4065002
0!
#4070002
b110000110 %
1!
#4075002
0!
#4080002
b110000111 %
1!
#4085002
0!
#4090002
b110001000 %
1!
#4095002
0!
#4100002
b110001001 %
1!
#4105002
0!
#4110002
b110001010 %
1!
#4115002
0!
#4120002
b110001011 %
1!
#4125002
0!
#4130002
b110001100 %
1!
#4135002
0!
#4140002
b110001101 %
1!
#4145002
0!
#4150002
b110001110 %
1!
#4155002
0!
#4160002
b110001111 %
1!
#4165002
0!
#4170002
b110010000 %
1!
#4175002
0!
#4180002
b110010001 %
1!
#4185002
0!
#4190002
b110010010 %
1!
#4195002
0!
#4200002
b110010011 %
1!
#4205002
0!
#4210002
b110010100 %
1!
#4215002
0!
#4220002
b110010101 %
1!
#4225002
0!
#4230002
b110010110 %
1!
#4235002
0!
#4240002
b110010111 %
1!
#4245002
0!
#4250002
b110011000 %
1!
#4255002
0!
#4260002
b110011001 %
1!
#4265002
0!
#4270002
b110011010 %
1!
#4275002
0!
#4280002
b110011011 %
1!
#4285002
0!
#4290002
b110011100 %
1!
#4295002
0!
#4300002
b110011101 %
1!
#4305002
0!
#4310002
b110011110 %
1!
#4315002
0!
#4320002
b110011111 %
1!
#4325002
0!
#4330002
b110100000 %
1!
#4335002
0!
#4340002
b110100001 %
1!
#4345002
0!
#4350002
b110100010 %
1!
#4355002
0!
#4360002
b110100011 %
1!
#4365002
0!
#4370002
b110100100 %
1!
#4375002
0!
#4380002
b110100101 %
1!
#4385002
0!
#4390002
b110100110 %
1!
#4395002
0!
#4400002
b110100111 %
1!
#4405002
0!
#4410002
b110101000 %
1!
#4415002
0!
#4420002
b110101001 %
1!
#4425002
0!
#4430002
b110101010 %
1!
#4435002
0!
#4440002
b110101011 %
1!
#4445002
0!
#4450002
b110101100 %
1!
#4455002
0!
#4460002
b110101101 %
1!
#4465002
0!
#4470002
b110101110 %
1!
#4475002
0!
#4480002
b110101111 %
1!
#4485002
0!
#4490002
b110110000 %
1!
#4495002
0!
#4500002
b110110001 %
1!
#4505002
0!
#4510002
b110110010 %
1!
#4515002
0!
#4520002
b110110011 %
1!
#4525002
0!
#4530002
b110110100 %
1!
#4535002
0!
#4540002
b110110101 %
1!
#4545002
0!
#4550002
b110110110 %
1!
#4555002
0!
#4560002
b110110111 %
1!
#4565002
0!
#4570002
b110111000 %
1!
#4575002
0!
#4580002
b110111001 %
1!
#4585002
0!
#4590002
b110111010 %
1!
#4595002
0!
#4600002
b110111011 %
1!
#4605002
0!
#4610002
b110111100 %
1!
#4615002
0!
#4620002
b110111101 %
1!
#4625002
0!
#4630002
b110111110 %
1!
#4635002
0!
#4640002
b110111111 %
1!
#4645002
0!
#4650002
b111000000 %
1!
#4655002
0!
#4660002
b111000001 %
1!
#4665002
0!
#4670002
b111000010 %
1!
#4675002
0!
#4680002
b111000011 %
1!
#4685002
0!
#4690002
b111000100 %
1!
#4695002
0!
#4700002
b111000101 %
1!
#4705002
0!
#4710002
b111000110 %
1!
#4715002
0!
#4720002
b111000111 %
1!
#4725002
0!
#4730002
b111001000 %
1!
#4735002
0!
#4740002
b111001001 %
1!
#4745002
0!
#4750002
b111001010 %
1!
#4755002
0!
#4760002
b111001011 %
1!
#4765002
0!
#4770002
b111001100 %
1!
#4775002
0!
#4780002
b111001101 %
1!
#4785002
0!
#4790002
b111001110 %
1!
#4795002
0!
#4800002
b111001111 %
1!
#4805002
0!
#4810002
b111010000 %
1!
#4815002
0!
#4820002
b111010001 %
1!
#4825002
0!
#4830002
b111010010 %
1!
#4835002
0!
#4840002
b111010011 %
1!
#4845002
0!
#4850002
b111010100 %
1!
#4855002
0!
#4860002
b111010101 %
1!
#4865002
0!
#4870002
b111010110 %
1!
#4875002
0!
#4880002
b111010111 %
1!
#4885002
0!
#4890002
b111011000 %
1!
#4895002
0!
#4900002
b111011001 %
1!
#4905002
0!
#4910002
b111011010 %
1!
#4915002
0!
#4920002
b111011011 %
1!
#4925002
0!
#4930002
b111011100 %
1!
#4935002
0!
#4940002
b111011101 %
1!
#4945002
0!
#4950002
b111011110 %
1!
#4955002
0!
#4960002
b111011111 %
1!
#4965002
0!
#4970002
b111100000 %
1!
#4975002
0!
#4980002
b111100001 %
1!
#4985002
0!
#4990002
b111100010 %
1!
#4995002
0!
#5000002
b111100011 %
1!
#5005002
0!
#5010002
b111100100 %
1!
#5015002
0!
#5020002
b111100101 %
1!
#5025002
0!
#5030002
b111100110 %
1!
#5035002
0!
#5040002
b111100111 %
1!
#5045002
0!
#5050002
b111101000 %
1!
#5055002
0!
#5060002
b111101001 %
1!
#5065002
0!
#5070002
b111101010 %
1!
#5075002
0!
#5080002
b111101011 %
1!
#5085002
0!
#5090002
b111101100 %
1!
#5095002
0!
#5100002
b111101101 %
1!
#5105002
0!
#5110002
b111101110 %
1!
#5115002
0!
#5120002
b111101111 %
1!
#5125002
0!
#5130002
b111110000 %
1!
#5135002
0!
#5140002
b111110001 %
1!
#5145002
0!
#5150002
b111110010 %
1!
#5155002
0!
#5160002
b111110011 %
1!
#5165002
0!
#5170002
b111110100 %
1!
#5175002
0!
#5180002
b111110101 %
1!
#5185002
0!
#5190002
b111110110 %
1!
#5195002
0!
#5200002
b111110111 %
1!
#5205002
0!
#5210002
b111111000 %
1!
#5215002
0!
#5220002
b111111001 %
1!
#5225002
0!
#5230002
b111111010 %
1!
#5235002
0!
#5240002
b111111011 %
1!
#5245002
0!
#5250002
b111111100 %
1!
#5255002
0!
#5260002
b111111101 %
1!
#5265002
0!
#5270002
b111111110 %
1!
#5275002
0!
#5280002
b111111111 %
1!
#5285002
0!
#5290002
b1000000000 %
1!
#5295002
0!
#5300002
b1000000001 %
1!
#5305002
0!
#5310002
b1000000010 %
1!
#5315002
0!
#5320002
b1000000011 %
1!
#5325002
0!
#5330002
b1000000100 %
1!
#5335002
0!
#5340002
b1000000101 %
1!
#5345002
0!
#5350002
b1000000110 %
1!
#5355002
0!
#5360002
b1000000111 %
1!
#5365002
0!
#5370002
b1000001000 %
1!
#5375002
0!
#5380002
b1000001001 %
1!
#5385002
0!
#5390002
b1000001010 %
1!
#5395002
0!
#5400002
b1000001011 %
1!
#5405002
0!
#5410002
b1000001100 %
1!
#5415002
0!
#5420002
b1000001101 %
1!
#5425002
0!
#5430002
b1000001110 %
1!
#5435002
0!
#5440002
b1000001111 %
1!
#5445002
0!
#5450002
b1000010000 %
1!
#5455002
0!
#5460002
b1000010001 %
1!
#5465002
0!
#5470002
b1000010010 %
1!
#5475002
0!
#5480002
b1000010011 %
1!
#5485002
0!
#5490002
b1000010100 %
1!
#5495002
0!
#5500002
b1000010101 %
1!
#5505002
0!
#5510002
b1000010110 %
1!
#5515002
0!
#5520002
b1000010111 %
1!
#5525002
0!
#5530002
b1000011000 %
1!
#5535002
0!
#5540002
b1000011001 %
1!
#5545002
0!
#5550002
b1000011010 %
1!
#5555002
0!
#5560002
b1000011011 %
1!
#5565002
0!
#5570002
b1000011100 %
1!
#5575002
0!
#5580002
b1000011101 %
1!
#5585002
0!
#5590002
b1000011110 %
1!
#5595002
0!
#5600002
b1000011111 %
1!
#5605002
0!
#5610002
b1000100000 %
1!
#5615002
0!
#5620002
b1000100001 %
1!
#5625002
0!
#5630002
b1000100010 %
1!
#5635002
0!
#5640002
b1000100011 %
1!
#5645002
0!
#5650002
b1000100100 %
1!
#5655002
0!
#5660002
b1000100101 %
1!
#5665002
0!
#5670002
b1000100110 %
1!
#5675002
0!
#5680002
b1000100111 %
1!
#5685002
0!
#5690002
b1000101000 %
1!
#5695002
0!
#5700002
b1000101001 %
1!
#5705002
0!
#5710002
b1000101010 %
1!
#5715002
0!
#5720002
b1000101011 %
1!
#5725002
0!
#5730002
b1000101100 %
1!
#5735002
0!
#5740002
b1000101101 %
1!
#5745002
0!
#5750002
b1000101110 %
1!
#5755002
0!
#5760002
b1000101111 %
1!
#5765002
0!
#5770002
b1000110000 %
1!
#5775002
0!
#5780002
b1000110001 %
1!
#5785002
0!
#5790002
b1000110010 %
1!
#5795002
0!
#5800002
b1000110011 %
1!
#5805002
0!
#5810002
b1000110100 %
1!
#5815002
0!
#5820002
b1000110101 %
1!
#5825002
0!
#5830002
b1000110110 %
1!
#5835002
0!
#5840002
b1000110111 %
1!
#5845002
0!
#5850002
b1000111000 %
1!
#5855002
0!
#5860002
b1000111001 %
1!
#5865002
0!
#5870002
b1000111010 %
1!
#5875002
0!
#5880002
b1000111011 %
1!
#5885002
0!
#5890002
b1000111100 %
1!
#5895002
0!
#5900002
b1000111101 %
1!
#5905002
0!
#5910002
b1000111110 %
1!
#5915002
0!
#5920002
b1000111111 %
1!
#5925002
0!
#5930002
b1001000000 %
1!
#5935002
0!
#5940002
b1001000001 %
1!
#5945002
0!
#5950002
b1001000010 %
1!
#5955002
0!
#5960002
b1001000011 %
1!
#5965002
0!
#5970002
b1001000100 %
1!
#5975002
0!
#5980002
b1001000101 %
1!
#5985002
0!
#5990002
b1001000110 %
1!
#5995002
0!
#6000002
b1001000111 %
1!
#6005002
0!
#6010002
b1001001000 %
1!
#6015002
0!
#6020002
b1001001001 %
1!
#6025002
0!
#6030002
b1001001010 %
1!
#6035002
0!
#6040002
b1001001011 %
1!
#6045002
0!
#6050002
b1001001100 %
1!
#6055002
0!
#6060002
b1001001101 %
1!
#6065002
0!
#6070002
b1001001110 %
1!
#6075002
0!
#6080002
b1001001111 %
1!
#6085002
0!
#6090002
b1001010000 %
1!
#6095002
0!
#6100002
b1001010001 %
1!
#6105002
0!
#6110002
b1001010010 %
1!
#6115002
0!
#6120002
b1001010011 %
1!
#6125002
0!
#6130002
b1001010100 %
1!
#6135002
0!
#6140002
b1001010101 %
1!
#6145002
0!
#6150002
b1001010110 %
1!
#6155002
0!
#6160002
b1001010111 %
1!
#6165002
0!
#6170002
b1001011000 %
1!
#6175002
0!
#6180002
b1001011001 %
1!
#6185002
0!
#6190002
b1001011010 %
1!
#6195002
0!
#6200002
b1001011011 %
1!
#6205002
0!
#6210002
b1001011100 %
1!
#6215002
0!
#6220002
b1001011101 %
1!
#6225002
0!
#6230002
b1001011110 %
1!
#6235002
0!
#6240002
b1001011111 %
1!
#6245002
0!
#6250002
b1001100000 %
1!
#6255002
0!
#6260002
b1001100001 %
1!
#6265002
0!
#6270002
b1001100010 %
1!
#6275002
0!
#6280002
b1001100011 %
1!
