week3/reference/prod_mac/mac_prod.v
// Production-style systolic MAC cell (TPU-leaning).
//
// 실제 NPU/TPU 의 MAC 셀에 가까운 형태 — mac_v2.v 의 saturation/overflow flag 를
// 의도적으로 제거. 입력 quantization 단계에서 range 보장한다고 가정.
//
// 특징:
//   1. Weight stationary       — weight_reg 에 한 번 로드, 여러 activation 재사용
//   2. Activation propagation  — act_in → act_out 1 cycle 지연 (옆 셀로 전달)
//   3. Partial sum chain       — psum_in + (act × weight) → psum_out (아래 셀로)
//   4. No saturation/overflow  — INT32 누적 폭으로 미리 막음 (1024 MAC 까지 안전)
//   5. Enable                  — clock gating 효과, idle 시 동적 전력 절감
//   6. Active-low reset        — 산업 표준
//   7. Parameterized widths    — INT4/INT8/INT16 재사용
//   8. Synthesis-clean         — VCD dump 는 `ifndef SYNTHESIS` 가드

module mac_prod #(
    parameter DATA_WIDTH = 8,
    parameter ACC_WIDTH  = 32
) (
    input  wire                          clk,
    input  wire                          rst_n,
    input  wire                          en,

    // Weight 로드 — matmul 시작 시 1회 strobe
    input  wire                          load_weight,
    input  wire signed [DATA_WIDTH-1:0]  weight_in,

    // Activation : left → right
    input  wire signed [DATA_WIDTH-1:0]  act_in,
    output reg  signed [DATA_WIDTH-1:0]  act_out,

    // Partial sum : top → bottom
    input  wire signed [ACC_WIDTH-1:0]   psum_in,
    output reg  signed [ACC_WIDTH-1:0]   psum_out
);

    reg signed [DATA_WIDTH-1:0] weight_reg;

    always @(posedge clk or negedge rst_n) begin
        if (!rst_n) begin
            weight_reg <= {DATA_WIDTH{1'b0}};
            act_out    <= {DATA_WIDTH{1'b0}};
            psum_out   <= {ACC_WIDTH{1'b0}};
        end else if (en) begin
            if (load_weight) begin
                weight_reg <= weight_in;
            end
            act_out  <= act_in;
            psum_out <= psum_in + (act_in * weight_reg);
        end
    end

`ifndef SYNTHESIS
`ifndef NO_VCD_DUMP
    initial begin
        $dumpfile("dump.vcd");
        $dumpvars(0, mac_prod);
    end
`endif
`endif

endmodule

week3/reference/prod_mac/dump.vcd
$date
	Fri May 22 15:07:44 2026
$end
$version
	Icarus Verilog
$end
$timescale
	1ps
$end
$scope module mac_prod $end
$var wire 8 ! act_in [7:0] $end
$var wire 1 " clk $end
$var wire 1 # en $end
$var wire 1 $ load_weight $end
$var wire 32 % psum_in [31:0] $end
$var wire 1 & rst_n $end
$var wire 8 ' weight_in [7:0] $end
$var parameter 32 ( ACC_WIDTH $end
$var parameter 32 ) DATA_WIDTH $end
$var reg 8 * act_out [7:0] $end
$var reg 32 + psum_out [31:0] $end
$var reg 8 , weight_reg [7:0] $end
$upscope $end
$enddefinitions $end
$comment Show the parameter values. $end
$dumpall
b1000 )
b100000 (
$end
#0
$dumpvars
b0 ,
b0 +
b0 *
b0 '
0&
b0 %
0$
1#
1"
b0 !
$end
#5000
0"
#10000
1&
1"
#15000
0"
#20000
1"
#25000
0"
b11 '
1$
#30000
b11 ,
1"
#35000
0"
b101 !
b0 '
0$
#40000
b1111 +
b101 *
1"
#45001
b0 +
b0 *
b0 ,
b0 !
0&
#50001
0"
#55001
1"
#60001
0"
#65001
1&
1"
#70001
0"
#75001
1"
#80001
0"
b100 '
1$
#85001
b100 ,
1"
#90001
0"
b1 !
b0 '
0$
#95001
b100 +
b1 *
1"
#100001
0"
b10 !
#105001
b1000 +
b10 *
1"
#110001
0"
b11 !
#115001
b1100 +
b11 *
1"
#120001
0"
b101 !
#125001
b10100 +
b101 *
1"
#130001
0"
b111 !
#135001
b11100 +
b111 *
1"
#140002
b0 +
b0 *
b0 ,
b0 !
0&
#145002
0"
#150002
1"
#155002
0"
#160002
1&
1"
#165002
0"
#170002
1"
#175002
0"
b1 '
1$
#180002
b1 ,
1"
#185002
0"
b111 !
b0 '
0$
#190002
b111 +
b111 *
1"
#195002
0"
b11111101 !
#200002
b11111111111111111111111111111101 +
b11111101 *
1"
#205002
0"
b1011 !
#210002
b1011 +
b1011 *
1"
#215002
0"
b11001 !
#220002
b11001 +
b11001 *
1"
#225002
0"
b11001110 !
#230002
b11111111111111111111111111001110 +
b11001110 *
1"
#235003
b0 +
b0 *
b0 ,
b0 !
0&
#240003
0"
#245003
1"
#250003
0"
#255003
1&
1"
#260003
0"
#265003
1"
#270003
0"
b10 '
1$
#275003
b10 ,
1"
#280003
0"
b11 !
b0 '
0$
#285003
b110 +
b11 *
1"
#290003
0"
b101 !
b110 %
#295003
b10000 +
b101 *
1"
#300003
0"
b111 !
b10000 %
#305003
b11110 +
b111 *
1"
#310003
0"
b1011 !
b11110 %
#315003
b110100 +
b1011 *
1"
#320003
b110100 %
#320004
b0 +
b0 *
b0 ,
b0 %
b0 !
0&
#325004
0"
#330004
1"
#335004
0"
#340004
1&
1"
#345004
0"
#350004
1"
#355004
0"
b11 '
1$
#360004
b11 ,
1"
#365004
0"
b101 !
b0 '
0$
#370004
b1111 +
b101 *
1"
#375004
0"
b1111100111 %
b1100100 !
0#
#380004
1"
#385004
0"
#390004
1"
#395004
0"
#400004
1"
#405004
0"
#410004
1"
#415004
0"
#420004
1"
#425005
b0 +
b0 *
b0 ,
b0 %
b0 !
1#
0&
#430005
0"
#435005
1"
#440005
0"
#445005
1&
1"
#450005
0"
#455005
1"
#460005
0"
b111 '
1$
#465005
b111 ,
1"
#470005
0"
b11011100 !
b0 '
0$
#475005
b11111111111111111111111100000100 +
b11011100 *
1"
#480005
0"
b100010 !
b11111111111111111111111100000100 %
#485005
b11111111111111111111111111110010 +
b100010 *
1"
#490005
0"
b11010110 !
b11111111111111111111111111110010 %
#495005
b11111111111111111111111011001100 +
b11010110 *
1"
#500005
0"
b11011010 !
b11111111111111111111111011001100 %
#505005
b11111111111111111111110111000010 +
b11011010 *
1"
#510005
0"
b11011 !
b11111111111111111111110111000010 %
#515005
b11111111111111111111111001111111 +
b11011 *
1"
#520005
0"
b11001 !
b11111111111111111111111001111111 %
#525005
b11111111111111111111111100101110 +
b11001 *
1"
#530005
0"
b110001 !
b11111111111111111111111100101110 %
#535005
b10000101 +
b110001 *
1"
#540005
0"
b110 !
b10000101 %
#545005
b10101111 +
b110 *
1"
#550005
0"
b1111 !
b10101111 %
#555005
b100011000 +
b1111 *
1"
#560005
0"
b11110011 !
b100011000 %
#565005
b10111101 +
b11110011 *
1"
#570005
0"
b11101111 !
b10111101 %
#575005
b1000110 +
b11101111 *
1"
#580005
0"
b11111001 !
b1000110 %
#585005
b10101 +
b11111001 *
1"
#590005
0"
b11010110 !
b10101 %
#595005
b11111111111111111111111011101111 +
b11010110 *
1"
#600005
0"
b11111000 !
b11111111111111111111111011101111 %
#605005
b11111111111111111111111010110111 +
b11111000 *
1"
#610005
0"
b11001 !
b11111111111111111111111010110111 %
#615005
b11111111111111111111111101100110 +
b11001 *
1"
#620005
0"
b100011 !
b11111111111111111111111101100110 %
#625005
b1011011 +
b100011 *
1"
#630005
0"
b11010110 !
b1011011 %
#635005
b11111111111111111111111100110101 +
b11010110 *
1"
#640005
0"
b11010011 !
b11111111111111111111111100110101 %
#645005
b11111111111111111111110111111010 +
b11010011 *
1"
#650005
0"
b10 !
b11111111111111111111110111111010 %
#655005
b11111111111111111111111000001000 +
b10 *
1"
#660005
0"
b10011 !
b11111111111111111111111000001000 %
#665005
b11111111111111111111111010001101 +
b10011 *
1"
#670005
0"
b101001 !
b11111111111111111111111010001101 %
#675005
b11111111111111111111111110101100 +
b101001 *
1"
#680005
0"
b0 !
b11111111111111111111111110101100 %
#685005
b0 *
1"
#690005
0"
b111 !
#695005
b11111111111111111111111111011101 +
b111 *
1"
#700005
0"
b11100001 !
b11111111111111111111111111011101 %
#705005
b11111111111111111111111100000100 +
b11100001 *
1"
#710005
0"
b10100 !
b11111111111111111111111100000100 %
#715005
b11111111111111111111111110010000 +
b10100 *
1"
#720005
0"
b11001110 !
b11111111111111111111111110010000 %
#725005
b11111111111111111111111000110010 +
b11001110 *
1"
#730005
0"
b11011000 !
b11111111111111111111111000110010 %
#735005
b11111111111111111111110100011010 +
b11011000 *
1"
#740005
0"
b11010111 !
b11111111111111111111110100011010 %
#745005
b11111111111111111111101111111011 +
b11010111 *
1"
#750005
0"
b100 !
b11111111111111111111101111111011 %
#755005
b11111111111111111111110000010111 +
b100 *
1"
#760005
0"
b11101110 !
b11111111111111111111110000010111 %
#765005
b11111111111111111111101110011001 +
b11101110 *
1"
#770005
0"
b11011 !
b11111111111111111111101110011001 %
#775005
b11111111111111111111110001010110 +
b11011 *
1"
#780005
0"
b10 !
b11111111111111111111110001010110 %
#785005
b11111111111111111111110001100100 +
b10 *
1"
#790005
0"
b101010 !
b11111111111111111111110001100100 %
#795005
b11111111111111111111110110001010 +
b101010 *
1"
#800005
0"
b11110100 !
b11111111111111111111110110001010 %
#805005
b11111111111111111111110100110110 +
b11110100 *
1"
#810005
0"
b11001 !
b11111111111111111111110100110110 %
#815005
b11111111111111111111110111100101 +
b11001 *
1"
#820005
0"
b101111 !
b11111111111111111111110111100101 %
#825005
b11111111111111111111111100101110 +
b101111 *
1"
#830005
0"
b11101000 !
b11111111111111111111111100101110 %
#835005
b11111111111111111111111010000110 +
b11101000 *
1"
#840005
0"
b10111 !
b11111111111111111111111010000110 %
#845005
b11111111111111111111111100100111 +
b10111 *
1"
#850005
0"
b11100000 !
b11111111111111111111111100100111 %
#855005
b11111111111111111111111001000111 +
b11100000 *
1"
#860005
0"
b11001 !
b11111111111111111111111001000111 %
#865005
b11111111111111111111111011110110 +
b11001 *
1"
#870005
0"
b1000 !
b11111111111111111111111011110110 %
#875005
b11111111111111111111111100101110 +
b1000 *
1"
#880005
0"
b10101 !
b11111111111111111111111100101110 %
#885005
b11111111111111111111111111000001 +
b10101 *
1"
#890005
0"
b1101 !
b11111111111111111111111111000001 %
#895005
b11100 +
b1101 *
1"
#900005
0"
b0 !
b11100 %
#905005
b0 *
1"
#910005
0"
b11100 !
#915005
b11100000 +
b11100 *
1"
#920005
0"
b11010101 !
b11100000 %
#925005
b11111111111111111111111110110011 +
b11010101 *
1"
#930005
0"
b11111 !
b11111111111111111111111110110011 %
#935005
b10001100 +
b11111 *
1"
#940005
0"
b11110100 !
b10001100 %
#945005
b111000 +
b11110100 *
1"
#950005
0"
b11010110 !
b111000 %
#955005
b11111111111111111111111100010010 +
b11010110 *
1"
#960005
0"
b11010011 !
b11111111111111111111111100010010 %
#965005
b11111111111111111111110111010111 +
b11010011 *
1"
#970005
0"
b11101 !
b11111111111111111111110111010111 %
#975005
b11111111111111111111111010100010 +
b11101 *
1"
#980005
0"
b11011010 !
b11111111111111111111111010100010 %
#985005
b11111111111111111111110110011000 +
b11011010 *
1"
#990005
0"
b11111000 !
b11111111111111111111110110011000 %
#995005
b11111111111111111111110101100000 +
b11111000 *
1"
#1000005
0"
b10111 !
b11111111111111111111110101100000 %
#1005005
b11111111111111111111111000000001 +
b10111 *
1"
#1010005
0"
b101111 !
b11111111111111111111111000000001 %
#1015005
b11111111111111111111111101001010 +
b101111 *
1"
#1020005
0"
b100001 !
b11111111111111111111111101001010 %
#1025005
b110001 +
b100001 *
1"
#1030005
0"
b11111111 !
b110001 %
#1035005
b101010 +
b11111111 *
1"
#1040005
0"
b11101011 !
b101010 %
#1045005
b11111111111111111111111110010111 +
b11101011 *
1"
#1050005
0"
b11111010 !
b11111111111111111111111110010111 %
#1055005
b11111111111111111111111101101101 +
b11111010 *
1"
#1060005
0"
b11010100 !
b11111111111111111111111101101101 %
#1065005
b11111111111111111111111000111001 +
b11010100 *
1"
#1070005
0"
b11010110 !
b11111111111111111111111000111001 %
#1075005
b11111111111111111111110100010011 +
b11010110 *
1"
#1080005
0"
b100 !
b11111111111111111111110100010011 %
#1085005
b11111111111111111111110100101111 +
b100 *
1"
#1090005
0"
b1011 !
b11111111111111111111110100101111 %
#1095005
b11111111111111111111110101111100 +
b1011 *
1"
#1100005
0"
b11110010 !
b11111111111111111111110101111100 %
#1105005
b11111111111111111111110100011010 +
b11110010 *
1"
#1110005
0"
b10010 !
b11111111111111111111110100011010 %
#1115005
b11111111111111111111110110011000 +
b10010 *
1"
#1120005
0"
b11011111 !
b11111111111111111111110110011000 %
#1125005
b11111111111111111111110010110001 +
b11011111 *
1"
#1130005
0"
b11110101 !
b11111111111111111111110010110001 %
#1135005
b11111111111111111111110001100100 +
b11110101 *
1"
#1140005
0"
b11111100 !
b11111111111111111111110001100100 %
#1145005
b11111111111111111111110001001000 +
b11111100 *
1"
#1150005
0"
b101010 !
b11111111111111111111110001001000 %
#1155005
b11111111111111111111110101101110 +
b101010 *
1"
#1160005
0"
b11010000 !
b11111111111111111111110101101110 %
#1165005
b11111111111111111111110000011110 +
b11010000 *
1"
#1170005
0"
b11110 !
b11111111111111111111110000011110 %
#1175005
b11111111111111111111110011110000 +
b11110 *
1"
#1180005
0"
b11010101 !
b11111111111111111111110011110000 %
#1185005
b11111111111111111111101111000011 +
b11010101 *
1"
#1190005
0"
b11110000 !
b11111111111111111111101111000011 %
#1195005
b11111111111111111111101101010011 +
b11110000 *
1"
#1200005
0"
b100000 !
b11111111111111111111101101010011 %
#1205005
b11111111111111111111110000110011 +
b100000 *
1"
#1210005
0"
b1100 !
b11111111111111111111110000110011 %
#1215005
b11111111111111111111110010000111 +
b1100 *
1"
#1220005
0"
b11001111 !
b11111111111111111111110010000111 %
#1225005
b11111111111111111111101100110000 +
b11001111 *
1"
#1230005
0"
b11110110 !
b11111111111111111111101100110000 %
#1235005
b11111111111111111111101011101010 +
b11110110 *
1"
#1240005
0"
b0 !
b11111111111111111111101011101010 %
#1245005
b0 *
1"
#1250005
0"
b1100 !
#1255005
b11111111111111111111101100111110 +
b1100 *
1"
#1260005
0"
b11011011 !
b11111111111111111111101100111110 %
#1265005
b11111111111111111111101000111011 +
b11011011 *
1"
#1270005
0"
b11100110 !
b11111111111111111111101000111011 %
#1275005
b11111111111111111111100110000101 +
b11100110 *
1"
#1280005
0"
b1100 !
b11111111111111111111100110000101 %
#1285005
b11111111111111111111100111011001 +
b1100 *
1"
#1290005
0"
b100 !
b11111111111111111111100111011001 %
#1295005
b11111111111111111111100111110101 +
b100 *
1"
#1300005
0"
b11100 !
b11111111111111111111100111110101 %
#1305005
b11111111111111111111101010111001 +
b11100 *
1"
#1310005
0"
b1000 !
b11111111111111111111101010111001 %
#1315005
b11111111111111111111101011110001 +
b1000 *
1"
#1320005
0"
b11100100 !
b11111111111111111111101011110001 %
#1325005
b11111111111111111111101000101101 +
b11100100 *
1"
#1330005
0"
b11101101 !
b11111111111111111111101000101101 %
#1335005
b11111111111111111111100110101000 +
b11101101 *
1"
#1340005
0"
b11111111111111111111100110101000 %
#1345005
b11111111111111111111100100100011 +
1"
#1350005
0"
b11111010 !
b11111111111111111111100100100011 %
#1355005
b11111111111111111111100011111001 +
b11111010 *
1"
#1360005
0"
b11011001 !
b11111111111111111111100011111001 %
#1365005
b11111111111111111111011111101000 +
b11011001 *
1"
#1370005
0"
b11101101 !
b11111111111111111111011111101000 %
#1375005
b11111111111111111111011101100011 +
b11101101 *
1"
#1380005
0"
b11100100 !
b11111111111111111111011101100011 %
#1385005
b11111111111111111111011010011111 +
b11100100 *
1"
#1390005
0"
b11011011 !
b11111111111111111111011010011111 %
#1395005
b11111111111111111111010110011100 +
b11011011 *
1"
#1400005
0"
b11100011 !
b11111111111111111111010110011100 %
#1405005
b11111111111111111111010011010001 +
b11100011 *
1"
#1410005
0"
b1000 !
b11111111111111111111010011010001 %
#1415005
b11111111111111111111010100001001 +
b1000 *
1"
#1420005
0"
b11010110 !
b11111111111111111111010100001001 %
#1425005
b11111111111111111111001111100011 +
b11010110 *
1"
#1430005
0"
b11101000 !
b11111111111111111111001111100011 %
#1435005
b11111111111111111111001100111011 +
b11101000 *
1"
#1440005
0"
b101111 !
b11111111111111111111001100111011 %
#1445005
b11111111111111111111010010000100 +
b101111 *
1"
#1450005
0"
b10010 !
b11111111111111111111010010000100 %
#1455005
b11111111111111111111010100000010 +
b10010 *
1"
#1460005
0"
b11000 !
b11111111111111111111010100000010 %
#1465005
b11111111111111111111010110101010 +
b11000 *
1"
